mesmerize_core/VERSION
mesmerize_core/__init__.py
mesmerize_core/batch_utils.py
mesmerize_core/movie_readers.py
mesmerize_core/utils.py
mesmerize_core/algorithms/__init__.py
mesmerize_core/algorithms/cnmf.py
mesmerize_core/algorithms/cnmfe.py
mesmerize_core/algorithms/mcorr.py
mesmerize_core/arrays/__init__.py
mesmerize_core/arrays/_base.py
mesmerize_core/arrays/_cnmf.py
mesmerize_core/arrays/_tiff.py
mesmerize_core/arrays/_video.py
mesmerize_core/caiman_extensions/__init__.py
mesmerize_core/caiman_extensions/_batch_exceptions.py
mesmerize_core/caiman_extensions/_utils.py
mesmerize_core/caiman_extensions/cache.py
mesmerize_core/caiman_extensions/cnmf.py
mesmerize_core/caiman_extensions/common.py
mesmerize_core/caiman_extensions/mcorr.py
mesmerize_core-0.5.0.dist-info/licenses/LICENSE
tests/__init__.py
tests/params.py
tests/test_core.py
mesmerize_core-0.5.0.dist-info/METADATA
mesmerize_core-0.5.0.dist-info/WHEEL
mesmerize_core-0.5.0.dist-info/top_level.txt
mesmerize_core-0.5.0.dist-info/RECORD
