Metadata-Version: 2.4
Name: mesmerize-core
Version: 0.5.0
Summary: High level pandas-based API for batch analysis of Calcium Imaging data using CaImAn
Home-page: https://github.com/nel-lab/mesmerize-core
Author: Kushal Kolar, Caitlin Lewis, Arjun Putcha
Author-email: 
License: Apache-Software-License
Classifier: Programming Language :: Python :: 3
Classifier: License :: OSI Approved :: Apache Software License
Classifier: Operating System :: POSIX :: Linux
Classifier: Operating System :: MacOS :: MacOS X
Classifier: Operating System :: Microsoft :: Windows :: Windows 10
Classifier: Topic :: Scientific/Engineering :: Bio-Informatics
Classifier: Topic :: Scientific/Engineering :: Image Recognition
Classifier: Topic :: Scientific/Engineering :: Information Analysis
Classifier: Intended Audience :: Science/Research
License-File: LICENSE
Requires-Dist: pandas>=1.5.0
Requires-Dist: pytest
Requires-Dist: requests
Requires-Dist: tqdm
Requires-Dist: numpy
Requires-Dist: click
Requires-Dist: psutil
Requires-Dist: jupyterlab
Requires-Dist: filelock
Requires-Dist: mslex
Dynamic: author
Dynamic: classifier
Dynamic: description
Dynamic: description-content-type
Dynamic: home-page
Dynamic: license
Dynamic: license-file
Dynamic: requires-dist
Dynamic: summary
